cv_toolkit/__init__.py
cv_toolkit/camera_calibration.py
cv_toolkit/cli.py
cv_toolkit/code_display.py
cv_toolkit/edge_line_corner_detection.py
cv_toolkit/fundamental_matrix.py
cv_toolkit/geometric_transforms.py
cv_toolkit/homography.py
cv_toolkit/image_processing.py
cv_toolkit/perspective_transform.py
cv_toolkit/sift_descriptor.py
cv_toolkit/surf_hog_descriptor.py
cv_toolkit_new-0.1.3.dist-info/licenses/LICENSE
cv_toolkit_new-0.1.3.dist-info/METADATA
cv_toolkit_new-0.1.3.dist-info/WHEEL
cv_toolkit_new-0.1.3.dist-info/entry_points.txt
cv_toolkit_new-0.1.3.dist-info/top_level.txt
cv_toolkit_new-0.1.3.dist-info/RECORD
